[
  {
    "skillName": "cplusplus",
    "title": "C++",
    "image": "/skills-icon/c-32.png",
    "keySkill": true,
    "type": "softSkills",
    "level": {
      "none": 1,
      "junior": 1,
      "middle": 0,
      "senior": 2,
      "expert": 1
    },
    "targetLevel": {
      "none": 0,
      "junior": 1,
      "middle": 1,
      "senior": 2,
      "expert": 2
    }
  },
  {
    "skillName": "java",
    "title": "Java",
    "image": "/skills-icon/java.png",
    "keySkill": true,
    "type": "softSkills",
    "level": {
      "none": 1,
      "junior": 1,
      "middle": 0,
      "senior": 1,
      "expert": 1
    },
    "targetLevel": {
      "none": 0,
      "junior": 0,
      "middle": 0,
      "senior": 2,
      "expert": 2
    }
  },
  {
    "skillName": "python",
    "title": "Python дабуди дабудай дляДлинны",
    "image": "/skills-icon/python.png",
    "keySkill": true,
    "type": "hardSkills",
    "level": {
      "none": 0,
      "junior": 0,
      "middle": 0,
      "senior": 2,
      "expert": 0
    },
    "targetLevel": {
      "none": 0,
      "junior": 0,
      "middle": 0,
      "senior": 2,
      "expert": 0
    }
  }
]
